sectoolkit/__init__.py
sectoolkit/config.py
sectoolkit/limiter.py
sectoolkit/secfiling.py
sectoolkit/secmeta.py
sectoolkit/utils.py
sectoolkit/formparsers/__init__.py
sectoolkit/formparsers/parser_13D.py
sectoolkit/formparsers/parser_base.py
sectoolkit-0.2.4.dist-info/LICENSE
sectoolkit-0.2.4.dist-info/METADATA
sectoolkit-0.2.4.dist-info/WHEEL
sectoolkit-0.2.4.dist-info/top_level.txt
sectoolkit-0.2.4.dist-info/RECORD
