Metadata-Version: 2.1
Name: sectoolkit
Version: 0.2.4
Summary: Tools for working with Securities and Exchange Commission (SEC) indices, SGML header files, filing archives and individual filing documents.
Home-page: https://github.com/dlouton/sectoolkit
Author: Dave Louton
Author-email: dlouton@bryant.edu
License: MIT
Platform: UNKNOWN
Classifier: License :: OSI Approved :: MIT License
Classifier: Programming Language :: Python :: 3
Classifier: Programming Language :: Python :: 3.7
Requires-Dist: bs4
Requires-Dist: numpy
Requires-Dist: pandas
Requires-Dist: xmltodict
Requires-Dist: tqdm
